Workbook

Sheet Sales Data
A1: Month | B1: Region | C1: Sales Rep | D1: Product | E1: Units Sold | F1: Unit Price (₹) | G1: Revenue (₹) | H1: Target (₹) | I1: Achievement (%) | J1: Expenses (₹) | K1: Net Profit (₹)
A2: Jan | B2: North | C2: Arjun Kumar | D2: Product A | E2: 377 | F2: 500 | G2: =E2*F2 -> 188500 | H2: 552451 | I2: =IF(H2=0,0,G2/H2) -> 0.34120673 | J2: 122097 | K2: =G2-J2 -> 66403
A3: Jan | B3: North | C3: Arjun Kumar | D3: Product B | E3: 175 | F3: 999 | G3: =E3*F3 -> 174825 | H3: 792632 | I3: =IF(H3=0,0,G3/H3) -> 0.22056263 | J3: 76868 | K3: =G3-J3 -> 97957
A4: Jan | B4: North | C4: Arjun Kumar | D4: Product C | E4: 396 | F4: 4999 | G4: =E4*F4 -> 1979604 | H4: 682323 | I4: =IF(H4=0,0,G4/H4) -> 2.9012711 | J4: 160604 | K4: =G4-J4 -> 1819000
A5: Jan | B5: North | C5: Arjun Kumar | D5: Product D | E5: 66 | F5: 500 | G5: =E5*F5 -> 33000 | H5: 696493 | I5: =IF(H5=0,0,G5/H5) -> 0.047380232 | J5: 107314 | K5: =G5-J5 -> -74314
A6: Jan | B6: North | C6: Priya Nair | D6: Product A | E6: 169 | F6: 4999 | G6: =E6*F6 -> 844831 | H6: 1762524 | I6: =IF(H6=0,0,G6/H6) -> 0.47933021 | J6: 56956 | K6: =G6-J6 -> 787875
A7: Jan | B7: North | C7: Priya Nair | D7: Product B | E7: 337 | F7: 999 | G7: =E7*F7 -> 336663 | H7: 1862906 | I7: =IF(H7=0,0,G7/H7) -> 0.18071926 | J7: 192853 | K7: =G7-J7 -> 143810
A8: Jan | B8: North | C8: Priya Nair | D8: Product C | E8: 264 | F8: 999 | G8: =E8*F8 -> 263736 | H8: 1442059 | I8: =IF(H8=0,0,G8/H8) -> 0.18288849 | J8: 122926 | K8: =G8-J8 -> 140810
A9: Jan | B9: North | C9: Priya Nair | D9: Product D | E9: 53 | F9: 999 | G9: =E9*F9 -> 52947 | H9: 1964104 | I9: =IF(H9=0,0,G9/H9) -> 0.02695733 | J9: 160785 | K9: =G9-J9 -> -107838
A10: Jan | B10: South | C10: Rahul Verma | D10: Product A | E10: 224 | F10: 1499 | G10: =E10*F10 -> 335776 | H10: 826064 | I10: =IF(H10=0,0,G10/H10) -> 0.40647698 | J10: 106443 | K10: =G10-J10 -> 229333
A11: Jan | B11: South | C11: Rahul Verma | D11: Product B | E11: 222 | F11: 500 | G11: =E11*F11 -> 111000 | H11: 694502 | I11: =IF(H11=0,0,G11/H11) -> 0.15982675 | J11: 149595 | K11: =G11-J11 -> -38595
A12: Jan | B12: South | C12: Rahul Verma | D12: Product C | E12: 99 | F12: 1499 | G12: =E12*F12 -> 148401 | H12: 1221327 | I12: =IF(H12=0,0,G12/H12) -> 0.121508 | J12: 119342 | K12: =G12-J12 -> 29059
A13: Jan | B13: South | C13: Rahul Verma | D13: Product D | E13: 72 | F13: 2499 | G13: =E13*F13 -> 179928 | H13: 1624551 | I13: =IF(H13=0,0,G13/H13) -> 0.11075553 | J13: 82722 | K13: =G13-J13 -> 97206
... A385: Dec | B385: West | C385: Anjali Singh | D385: Product D | E385: 344 | F385: 2499 | G385: =E385*F385 -> 859656 | H385: 1702506 | I385: =IF(H385=0,0,G385/H385) -> 0.50493567 | J385: 156017 | K385: =G385-J385 -> 703639

Sheet Monthly Summary
A1: Monthly Sales Performance Summary
A2: FY 2024 | All Regions | All Products
A4: Month | B4: Total Revenue (₹) | C4: Total Target (₹) | D4: Achievement (%) | E4: Units Sold | F4: Total Expenses (₹) | G4: Net Profit (₹) | H4: MoM Growth (%)
A5: Jan | B5: =SUMPRODUCT(('Sales Data'!A$2:A$385=A5)*'Sales Data'!G$2:G$385) -> 13830106 | C5: =SUMPRODUCT(('Sales Data'!A$2:A$385=A5)*'Sales Data'!H$2:H$385) -> 39107602 | D5: =IF(C5=0,0,B5/C5) -> 0.35364239 | E5: =SUMPRODUCT(('Sales Data'!A$2:A$385=A5)*'Sales Data'!E$2:E$385) -> 7242 | F5: =SUMPRODUCT(('Sales Data'!A$2:A$385=A5)*'Sales Data'!J$2:J$385) -> 4018521 | G5: =B5-F5 -> 9811585 | H5: =IF(ROW()=5,"",(B5-B4)/B4)
A6: Feb | B6: =SUMPRODUCT(('Sales Data'!A$2:A$385=A6)*'Sales Data'!G$2:G$385) -> 17374718 | C6: =SUMPRODUCT(('Sales Data'!A$2:A$385=A6)*'Sales Data'!H$2:H$385) -> 37861343 | D6: =IF(C6=0,0,B6/C6) -> 0.4589039 | E6: =SUMPRODUCT(('Sales Data'!A$2:A$385=A6)*'Sales Data'!E$2:E$385) -> 7731 | F6: =SUMPRODUCT(('Sales Data'!A$2:A$385=A6)*'Sales Data'!J$2:J$385) -> 4070956 | G6: =B6-F6 -> 13303762 | H6: =IF(ROW()=5,"",(B6-B5)/B5) -> 0.25629681
A7: Mar | B7: =SUMPRODUCT(('Sales Data'!A$2:A$385=A7)*'Sales Data'!G$2:G$385) -> 17025730 | C7: =SUMPRODUCT(('Sales Data'!A$2:A$385=A7)*'Sales Data'!H$2:H$385) -> 38247090 | D7: =IF(C7=0,0,B7/C7) -> 0.44515099 | E7: =SUMPRODUCT(('Sales Data'!A$2:A$385=A7)*'Sales Data'!E$2:E$385) -> 7724 | F7: =SUMPRODUCT(('Sales Data'!A$2:A$385=A7)*'Sales Data'!J$2:J$385) -> 3493018 | G7: =B7-F7 -> 13532712 | H7: =IF(ROW()=5,"",(B7-B6)/B6) -> -0.020085966
A8: Apr | B8: =SUMPRODUCT(('Sales Data'!A$2:A$385=A8)*'Sales Data'!G$2:G$385) -> 14874430 | C8: =SUMPRODUCT(('Sales Data'!A$2:A$385=A8)*'Sales Data'!H$2:H$385) -> 40903223 | D8: =IF(C8=0,0,B8/C8) -> 0.36364934 | E8: =SUMPRODUCT(('Sales Data'!A$2:A$385=A8)*'Sales Data'!E$2:E$385) -> 6737 | F8: =SUMPRODUCT(('Sales Data'!A$2:A$385=A8)*'Sales Data'!J$2:J$385) -> 4002241 | G8: =B8-F8 -> 10872189 | H8: =IF(ROW()=5,"",(B8-B7)/B7) -> -0.12635582
A9: May | B9: =SUMPRODUCT(('Sales Data'!A$2:A$385=A9)*'Sales Data'!G$2:G$385) -> 15586311 | C9: =SUMPRODUCT(('Sales Data'!A$2:A$385=A9)*'Sales Data'!H$2:H$385) -> 44422939 | D9: =IF(C9=0,0,B9/C9) -> 0.35086177 | E9: =SUMPRODUCT(('Sales Data'!A$2:A$385=A9)*'Sales Data'!E$2:E$385) -> 7229 | F9: =SUMPRODUCT(('Sales Data'!A$2:A$385=A9)*'Sales Data'!J$2:J$385) -> 4150167 | G9: =B9-F9 -> 11436144 | H9: =IF(ROW()=5,"",(B9-B8)/B8) -> 0.04785938
A10: Jun | B10: =SUMPRODUCT(('Sales Data'!A$2:A$385=A10)*'Sales Data'!G$2:G$385) -> 12262960 | C10: =SUMPRODUCT(('Sales Data'!A$2:A$385=A10)*'Sales Data'!H$2:H$385) -> 41811761 | D10: =IF(C10=0,0,B10/C10) -> 0.29328973 | E10: =SUMPRODUCT(('Sales Data'!A$2:A$385=A10)*'Sales Data'!E$2:E$385) -> 7624 | F10: =SUMPRODUCT(('Sales Data'!A$2:A$385=A10)*'Sales Data'!J$2:J$385) -> 3954860 | G10: =B10-F10 -> 8308100 | H10: =IF(ROW()=5,"",(B10-B9)/B9) -> -0.21322242
A11: Jul | B11: =SUMPRODUCT(('Sales Data'!A$2:A$385=A11)*'Sales Data'!G$2:G$385) -> 18462338 | C11: =SUMPRODUCT(('Sales Data'!A$2:A$385=A11)*'Sales Data'!H$2:H$385) -> 39843393 | D11: =IF(C11=0,0,B11/C11) -> 0.46337263 | E11: =SUMPRODUCT(('Sales Data'!A$2:A$385=A11)*'Sales Data'!E$2:E$385) -> 7112 | F11: =SUMPRODUCT(('Sales Data'!A$2:A$385=A11)*'Sales Data'!J$2:J$385) -> 3731919 | G11: =B11-F11 -> 14730419 | H11: =IF(ROW()=5,"",(B11-B10)/B10) -> 0.50553684
A12: Aug | B12: =SUMPRODUCT(('Sales Data'!A$2:A$385=A12)*'Sales Data'!G$2:G$385) -> 19783721 | C12: =SUMPRODUCT(('Sales Data'!A$2:A$385=A12)*'Sales Data'!H$2:H$385) -> 38216231 | D12: =IF(C12=0,0,B12/C12) -> 0.5176785 | E12: =SUMPRODUCT(('Sales Data'!A$2:A$385=A12)*'Sales Data'!E$2:E$385) -> 8463 | F12: =SUMPRODUCT(('Sales Data'!A$2:A$385=A12)*'Sales Data'!J$2:J$385) -> 3890666 | G12: =B12-F12 -> 15893055 | H12: =IF(ROW()=5,"",(B12-B11)/B11) -> 0.071571813
A13: Sep | B13: =SUMPRODUCT(('Sales Data'!A$2:A$385=A13)*'Sales Data'!G$2:G$385) -> 14458921 | C13: =SUMPRODUCT(('Sales Data'!A$2:A$385=A13)*'Sales Data'!H$2:H$385) -> 44394420 | D13: =IF(C13=0,0,B13/C13) -> 0.32569231 | E13: =SUMPRODUCT(('Sales Data'!A$2:A$385=A13)*'Sales Data'!E$2:E$385) -> 7381 | F13: =SUMPRODUCT(('Sales Data'!A$2:A$385=A13)*'Sales Data'!J$2:J$385) -> 4031580 | G13: =B13-F13 -> 10427341 | H13: =IF(ROW()=5,"",(B13-B12)/B12) -> -0.26915058
A14: Oct | B14: =SUMPRODUCT(('Sales Data'!A$2:A$385=A14)*'Sales Data'!G$2:G$385) -> 14184098 | C14: =SUMPRODUCT(('Sales Data'!A$2:A$385=A14)*'Sales Data'!H$2:H$385) -> 42574981 | D14: =IF(C14=0,0,B14/C14) -> 0.33315571 | E14: =SUMPRODUCT(('Sales Data'!A$2:A$385=A14)*'Sales Data'!E$2:E$385) -> 7534 | F14: =SUMPRODUCT(('Sales Data'!A$2:A$385=A14)*'Sales Data'!J$2:J$385) -> 4060669 | G14: =B14-F14 -> 10123429 | H14: =IF(ROW()=5,"",(B14-B13)/B13) -> -0.019007158
A15: Nov | B15: =SUMPRODUCT(('Sales Data'!A$2:A$385=A15)*'Sales Data'!G$2:G$385) -> 13809449 | C15: =SUMPRODUCT(('Sales Data'!A$2:A$385=A15)*'Sales Data'!H$2:H$385) -> 36236684 | D15: =IF(C15=0,0,B15/C15) -> 0.38109031 | E15: =SUMPRODUCT(('Sales Data'!A$2:A$385=A15)*'Sales Data'!E$2:E$385) -> 7205 | F15: =SUMPRODUCT(('Sales Data'!A$2:A$385=A15)*'Sales Data'!J$2:J$385) -> 4068949 | G15: =B15-F15 -> 9740500 | H15: =IF(ROW()=5,"",(B15-B14)/B14) -> -0.026413312
A16: Dec | B16: =SUMPRODUCT(('Sales Data'!A$2:A$385=A16)*'Sales Data'!G$2:G$385) -> 16281210 | C16: =SUMPRODUCT(('Sales Data'!A$2:A$385=A16)*'Sales Data'!H$2:H$385) -> 41458521 | D16: =IF(C16=0,0,B16/C16) -> 0.39271083 | E16: =SUMPRODUCT(('Sales Data'!A$2:A$385=A16)*'Sales Data'!E$2:E$385) -> 6277 | F16: =SUMPRODUCT(('Sales Data'!A$2:A$385=A16)*'Sales Data'!J$2:J$385) -> 4156699 | G16: =B16-F16 -> 12124511 | H16: =IF(ROW()=5,"",(B16-B15)/B15) -> 0.17899056
A17: TOTAL | B17: =SUM(B5:B16) -> 187933992 | C17: =SUM(C5:C16) -> 485078188 | D17: =IF(C17=0,0,B17/C17) -> 0.38743031 | E17: =SUM(E5:E16) -> 88259 | F17: =SUM(F5:F16) -> 47630245 | G17: =SUM(G5:G16) -> 140303747

Sheet Regional Summary
A1: Regional Sales Performance Dashboard
A3: Region | B3: Revenue (₹) | C3: Target (₹) | D3: Achievement (%) | E3: Units Sold | F3: Expenses (₹) | G3: Net Profit (₹)
A4: North | B4: =SUMPRODUCT(('Sales Data'!B$2:B$385=A4)*'Sales Data'!G$2:G$385) -> 49112161 | C4: =SUMPRODUCT(('Sales Data'!B$2:B$385=A4)*'Sales Data'!H$2:H$385) -> 122547577 | D4: =IF(C4=0,0,B4/C4) -> 0.40075995 | E4: =SUMPRODUCT(('Sales Data'!B$2:B$385=A4)*'Sales Data'!E$2:E$385) -> 21463 | F4: =SUMPRODUCT(('Sales Data'!B$2:B$385=A4)*'Sales Data'!J$2:J$385) -> 11985678 | G4: =B4-F4 -> 37126483
A5: South | B5: =SUMPRODUCT(('Sales Data'!B$2:B$385=A5)*'Sales Data'!G$2:G$385) -> 40462753 | C5: =SUMPRODUCT(('Sales Data'!B$2:B$385=A5)*'Sales Data'!H$2:H$385) -> 118744399 | D5: =IF(C5=0,0,B5/C5) -> 0.34075504 | E5: =SUMPRODUCT(('Sales Data'!B$2:B$385=A5)*'Sales Data'!E$2:E$385) -> 21773 | F5: =SUMPRODUCT(('Sales Data'!B$2:B$385=A5)*'Sales Data'!J$2:J$385) -> 11263677 | G5: =B5-F5 -> 29199076
A6: East | B6: =SUMPRODUCT(('Sales Data'!B$2:B$385=A6)*'Sales Data'!G$2:G$385) -> 50750453 | C6: =SUMPRODUCT(('Sales Data'!B$2:B$385=A6)*'Sales Data'!H$2:H$385) -> 120904785 | D6: =IF(C6=0,0,B6/C6) -> 0.41975554 | E6: =SUMPRODUCT(('Sales Data'!B$2:B$385=A6)*'Sales Data'!E$2:E$385) -> 23093 | F6: =SUMPRODUCT(('Sales Data'!B$2:B$385=A6)*'Sales Data'!J$2:J$385) -> 11872925 | G6: =B6-F6 -> 38877528
A7: West | B7: =SUMPRODUCT(('Sales Data'!B$2:B$385=A7)*'Sales Data'!G$2:G$385) -> 47608625 | C7: =SUMPRODUCT(('Sales Data'!B$2:B$385=A7)*'Sales Data'!H$2:H$385) -> 122881427 | D7: =IF(C7=0,0,B7/C7) -> 0.38743548 | E7: =SUMPRODUCT(('Sales Data'!B$2:B$385=A7)*'Sales Data'!E$2:E$385) -> 21930 | F7: =SUMPRODUCT(('Sales Data'!B$2:B$385=A7)*'Sales Data'!J$2:J$385) -> 12507965 | G7: =B7-F7 -> 35100660
A8: TOTAL | B8: =SUM(B4:B7) -> 187933992 | C8: =SUM(C4:C7) -> 485078188 | D8: =IF(C8=0,0,B8/C8) -> 0.38743031 | E8: =SUM(E4:E7) -> 88259 | F8: =SUM(F4:F7) -> 47630245 | G8: =SUM(G4:G7) -> 140303747

Sheet Rep Leaderboard
A1: Sales Rep Performance Leaderboard
A3: Rank | B3: Sales Rep | C3: Region | D3: Revenue (₹) | E3: Achievement (%) | F3: Net Profit (₹)
A4: 1 | B4: Arjun Kumar | C4: North | D4: =SUMPRODUCT(('Sales Data'!C$2:C$385=B4)*'Sales Data'!G$2:G$385) -> 24263774 | E4: =SUMPRODUCT(('Sales Data'!C$2:C$385=B4)*'Sales Data'!G$2:G$385)/SUMPRODUCT(('Sales Data'!C$2:C$385=B4)*'Sales Data'!H$2:H$385) -> 0.40593442 | F4: =SUMPRODUCT(('Sales Data'!C$2:C$385=B4)*'Sales Data'!K$2:K$385) -> 18410424
A5: 2 | B5: Priya Nair | C5: North | D5: =SUMPRODUCT(('Sales Data'!C$2:C$385=B5)*'Sales Data'!G$2:G$385) -> 24848387 | E5: =SUMPRODUCT(('Sales Data'!C$2:C$385=B5)*'Sales Data'!G$2:G$385)/SUMPRODUCT(('Sales Data'!C$2:C$385=B5)*'Sales Data'!H$2:H$385) -> 0.39583296 | F5: =SUMPRODUCT(('Sales Data'!C$2:C$385=B5)*'Sales Data'!K$2:K$385) -> 18716059
A6: 3 | B6: Rahul Verma | C6: South | D6: =SUMPRODUCT(('Sales Data'!C$2:C$385=B6)*'Sales Data'!G$2:G$385) -> 14635025 | E6: =SUMPRODUCT(('Sales Data'!C$2:C$385=B6)*'Sales Data'!G$2:G$385)/SUMPRODUCT(('Sales Data'!C$2:C$385=B6)*'Sales Data'!H$2:H$385) -> 0.24812866 | F6: =SUMPRODUCT(('Sales Data'!C$2:C$385=B6)*'Sales Data'!K$2:K$385) -> 8993944
A7: 4 | B7: Deepa Menon | C7: South | D7: =SUMPRODUCT(('Sales Data'!C$2:C$385=B7)*'Sales Data'!G$2:G$385) -> 25827728 | E7: =SUMPRODUCT(('Sales Data'!C$2:C$385=B7)*'Sales Data'!G$2:G$385)/SUMPRODUCT(('Sales Data'!C$2:C$385=B7)*'Sales Data'!H$2:H$385) -> 0.43217065 | F7: =SUMPRODUCT(('Sales Data'!C$2:C$385=B7)*'Sales Data'!K$2:K$385) -> 20205132
A8: 5 | B8: Amit Shah | C8: East | D8: =SUMPRODUCT(('Sales Data'!C$2:C$385=B8)*'Sales Data'!G$2:G$385) -> 24648676 | E8: =SUMPRODUCT(('Sales Data'!C$2:C$385=B8)*'Sales Data'!G$2:G$385)/SUMPRODUCT(('Sales Data'!C$2:C$385=B8)*'Sales Data'!H$2:H$385) -> 0.4096127 | F8: =SUMPRODUCT(('Sales Data'!C$2:C$385=B8)*'Sales Data'!K$2:K$385) -> 19070340
A9: 6 | B9: Sunita Roy | C9: East | D9: =SUMPRODUCT(('Sales Data'!C$2:C$385=B9)*'Sales Data'!G$2:G$385) -> 26101777 | E9: =SUMPRODUCT(('Sales Data'!C$2:C$385=B9)*'Sales Data'!G$2:G$385)/SUMPRODUCT(('Sales Data'!C$2:C$385=B9)*'Sales Data'!H$2:H$385) -> 0.42980591 | F9: =SUMPRODUCT(('Sales Data'!C$2:C$385=B9)*'Sales Data'!K$2:K$385) -> 19807188
A10: 7 | B10: Vikram Iyer | C10: West | D10: =SUMPRODUCT(('Sales Data'!C$2:C$385=B10)*'Sales Data'!G$2:G$385) -> 27579253 | E10: =SUMPRODUCT(('Sales Data'!C$2:C$385=B10)*'Sales Data'!G$2:G$385)/SUMPRODUCT(('Sales Data'!C$2:C$385=B10)*'Sales Data'!H$2:H$385) -> 0.46669287 | F10: =SUMPRODUCT(('Sales Data'!C$2:C$385=B10)*'Sales Data'!K$2:K$385) -> 21228651
A11: 8 | B11: Anjali Singh | C11: West | D11: =SUMPRODUCT(('Sales Data'!C$2:C$385=B11)*'Sales Data'!G$2:G$385) -> 20029372 | E11: =SUMPRODUCT(('Sales Data'!C$2:C$385=B11)*'Sales Data'!G$2:G$385)/SUMPRODUCT(('Sales Data'!C$2:C$385=B11)*'Sales Data'!H$2:H$385) -> 0.3140072 | F11: =SUMPRODUCT(('Sales Data'!C$2:C$385=B11)*'Sales Data'!K$2:K$385) -> 13872009

Sheet Product Analysis
A1: Product Performance Analysis
A3: Product | B3: Revenue (₹) | C3: Units Sold | D3: Avg Unit Price (₹) | E3: Expenses (₹) | F3: Net Profit (₹)
A4: Product A | B4: =SUMPRODUCT(('Sales Data'!D$2:D$385=A4)*'Sales Data'!G$2:G$385) -> 44224918 | C4: =SUMPRODUCT(('Sales Data'!D$2:D$385=A4)*'Sales Data'!E$2:E$385) -> 22174 | D4: =IF(C4=0,0,B4/C4) -> 1994.4493 | E4: =SUMPRODUCT(('Sales Data'!D$2:D$385=A4)*'Sales Data'!J$2:J$385) -> 12118324 | F4: =B4-E4 -> 32106594
A5: Product B | B5: =SUMPRODUCT(('Sales Data'!D$2:D$385=A5)*'Sales Data'!G$2:G$385) -> 51792878 | C5: =SUMPRODUCT(('Sales Data'!D$2:D$385=A5)*'Sales Data'!E$2:E$385) -> 22817 | D5: =IF(C5=0,0,B5/C5) -> 2269.925 | E5: =SUMPRODUCT(('Sales Data'!D$2:D$385=A5)*'Sales Data'!J$2:J$385) -> 11397426 | F5: =B5-E5 -> 40395452
A6: Product C | B6: =SUMPRODUCT(('Sales Data'!D$2:D$385=A6)*'Sales Data'!G$2:G$385) -> 48276413 | C6: =SUMPRODUCT(('Sales Data'!D$2:D$385=A6)*'Sales Data'!E$2:E$385) -> 21758 | D6: =IF(C6=0,0,B6/C6) -> 2218.7891 | E6: =SUMPRODUCT(('Sales Data'!D$2:D$385=A6)*'Sales Data'!J$2:J$385) -> 12028058 | F6: =B6-E6 -> 36248355
A7: Product D | B7: =SUMPRODUCT(('Sales Data'!D$2:D$385=A7)*'Sales Data'!G$2:G$385) -> 43639783 | C7: =SUMPRODUCT(('Sales Data'!D$2:D$385=A7)*'Sales Data'!E$2:E$385) -> 21510 | D7: =IF(C7=0,0,B7/C7) -> 2028.8137 | E7: =SUMPRODUCT(('Sales Data'!D$2:D$385=A7)*'Sales Data'!J$2:J$385) -> 12086437 | F7: =B7-E7 -> 31553346
A8: TOTAL | B8: =SUM(B4:B7) -> 187933992 | C8: =SUM(C4:C7) -> 88259 | D8: =IF(C8=0,0,B8/C8) -> 2129.3465 | E8: =SUM(E4:E7) -> 47630245 | F8: =SUM(F4:F7) -> 140303747

Sheet Executive Dashboard
A1: ⚡ EXECUTIVE SALES PERFORMANCE DASHBOARD ⚡
A2: FY 2024 | Consolidated View | All Regions & Products
A4: ='Monthly Summary'!B17 -> 187933992 | D4: ='Monthly Summary'!C17 -> 485078188 | G4: ='Monthly Summary'!D17 -> 0.38743031 | J4: ='Monthly Summary'!G17 -> 140303747
A8: Total Revenue | D8: Total Target | G8: Overall Achievement | J8: Net Profit
A10: ='Monthly Summary'!E17 -> 88259 | D10: ='Monthly Summary'!F17 -> 47630245 | G10: =INDEX('Regional Summary'!A4:A7,MATCH(MAX('Regional Summary'!B4:B7),'Regional Summary'!B4:B7,0)) -> East | J10: =INDEX('Product Analysis'!A4:A7,MATCH(MAX('Product Analysis'!B4:B7),'Product Analysis'!B4:B7,0)) -> Product B
A14: Units Sold | D14: Total Expenses | G14: Top Region | J14: Top Product
A16: Quick Regional Snapshot
A17: Region | B17: Revenue (₹) | C17: Target (₹) | D17: Achievement (%) | E17: Net Profit (₹)
A18: North | B18: ='Regional Summary'!B4 -> 49112161 | C18: ='Regional Summary'!C4 -> 122547577 | D18: ='Regional Summary'!D4 -> 0.40075995 | E18: ='Regional Summary'!G4 -> 37126483
A19: South | B19: ='Regional Summary'!B5 -> 40462753 | C19: ='Regional Summary'!C5 -> 118744399 | D19: ='Regional Summary'!D5 -> 0.34075504 | E19: ='Regional Summary'!G5 -> 29199076
A20: East | B20: ='Regional Summary'!B6 -> 50750453 | C20: ='Regional Summary'!C6 -> 120904785 | D20: ='Regional Summary'!D6 -> 0.41975554 | E20: ='Regional Summary'!G6 -> 38877528
A21: West | B21: ='Regional Summary'!B7 -> 47608625 | C21: ='Regional Summary'!C7 -> 122881427 | D21: ='Regional Summary'!D7 -> 0.38743548 | E21: ='Regional Summary'!G7 -> 35100660
